ollama/__init__.py
ollama/_client.py
ollama/_types.py
ollama_hass-0.1.7.dist-info/LICENSE
ollama_hass-0.1.7.dist-info/METADATA
ollama_hass-0.1.7.dist-info/WHEEL
ollama_hass-0.1.7.dist-info/RECORD
