Metadata-Version: 2.1
Name: ollama-hass
Version: 0.1.7
Summary: A fork of the official Python client for Ollama for Home Assistant.
Home-page: https://ollama.ai
License: MIT
Author: Ollama
Author-email: hello@ollama.com
Requires-Python: >=3.8,<4.0
Classifier: License :: OSI Approved :: MIT License
Classifier: Programming Language :: Python :: 3
Classifier: Programming Language :: Python :: 3.8
Classifier: Programming Language :: Python :: 3.9
Classifier: Programming Language :: Python :: 3.10
Classifier: Programming Language :: Python :: 3.11
Classifier: Programming Language :: Python :: 3.12
Requires-Dist: httpx (<1)
Project-URL: Repository, https://github.com/jmorganca/ollama-python
